freeproxy/__init__.py
freeproxy/client.py
freeproxy/proxy.py
freeproxy-1.0.2.dist-info/DESCRIPTION.rst
freeproxy-1.0.2.dist-info/entry_points.txt
freeproxy-1.0.2.dist-info/METADATA
freeproxy-1.0.2.dist-info/metadata.json
freeproxy-1.0.2.dist-info/RECORD
freeproxy-1.0.2.dist-info/top_level.txt
freeproxy-1.0.2.dist-info/WHEEL
