Metadata-Version: 1.1
Name: freeproxy
Version: 1.0.2
Summary: Get http proxies from some free proxy sites
Home-page: https://github.com/yieldnull/freeproxy
Author: YieldNull
Author-email: yieldnull@gmail.com
License: MIT
Keywords: proxy spider
Platform: any
Classifier: Intended Audience :: Developers
Classifier: License :: OSI Approved :: MIT License
Classifier: Operating System :: OS Independent
Classifier: Programming Language :: Python
Classifier: Programming Language :: Python :: 2
Classifier: Programming Language :: Python :: 2.6
Classifier: Programming Language :: Python :: 2.7
Classifier: Programming Language :: Python :: 3
Classifier: Programming Language :: Python :: 3.3
Classifier: Programming Language :: Python :: 3.4
Classifier: Programming Language :: Python :: 3.5
Classifier: Topic :: Internet :: WWW/HTTP
Classifier: Topic :: Software Development :: Libraries :: Python Modules
